cochl_sense/__init__.py
cochl_sense/constants.py
cochl_sense/file.py
cochl_sense/result.py
cochl_sense/stream.py
cochl_sense/proto/SenseClient_pb2.py
cochl_sense/proto/SenseClient_pb2_grpc.py
cochl_sense/proto/__init__.py
cochl_sense-1.0.0.dist-info/METADATA
cochl_sense-1.0.0.dist-info/WHEEL
cochl_sense-1.0.0.dist-info/top_level.txt
cochl_sense-1.0.0.dist-info/RECORD
