Metadata-Version: 2.1
Name: cochl-sense
Version: 1.0.0
Summary: Python Package for Cochlear.ai sense API 
Home-page: https://github.com/cochlearai/sense-python
Author: Cochlear.ai
Author-email: support@cochlear.ai
License: Apache License 2.0
Platform: UNKNOWN
Classifier: License :: OSI Approved :: Apache Software License
Classifier: Programming Language :: Python :: 3
Classifier: Programming Language :: Python :: 3.4
Classifier: Programming Language :: Python :: 3.5
Classifier: Programming Language :: Python :: 3.6
Classifier: Topic :: Scientific/Engineering :: Artificial Intelligence
Classifier: Intended Audience :: Developers
Requires-Dist: grpcio
Requires-Dist: protobuf
